pyfastaq/__init__.py
pyfastaq/_version.py
pyfastaq/app_fastaq.py
pyfastaq/caf.py
pyfastaq/genetic_codes.py
pyfastaq/intervals.py
pyfastaq/sequences.py
pyfastaq/tasks.py
pyfastaq/utils.py
pyfastaq/runners/__init__.py
pyfastaq/runners/acgtn_only.py
pyfastaq/runners/add_indels.py
pyfastaq/runners/caf_to_fastq.py
pyfastaq/runners/capillary_to_pairs.py
pyfastaq/runners/chunker.py
pyfastaq/runners/count_sequences.py
pyfastaq/runners/deinterleave.py
pyfastaq/runners/enumerate_names.py
pyfastaq/runners/expand_nucleotides.py
pyfastaq/runners/fasta_to_fastq.py
pyfastaq/runners/filter.py
pyfastaq/runners/get_ids.py
pyfastaq/runners/get_seq_flanking_gaps.py
pyfastaq/runners/interleave.py
pyfastaq/runners/make_random_contigs.py
pyfastaq/runners/merge.py
pyfastaq/runners/replace_bases.py
pyfastaq/runners/reverse_complement.py
pyfastaq/runners/scaffolds_to_contigs.py
pyfastaq/runners/search_for_seq.py
pyfastaq/runners/sequence_trim.py
pyfastaq/runners/sort_by_name.py
pyfastaq/runners/sort_by_size.py
pyfastaq/runners/split_by_base_count.py
pyfastaq/runners/strip_illumina_suffix.py
pyfastaq/runners/to_boulderio.py
pyfastaq/runners/to_fake_qual.py
pyfastaq/runners/to_fasta.py
pyfastaq/runners/to_mira_xml.py
pyfastaq/runners/to_orfs_gff.py
pyfastaq/runners/to_perfect_reads.py
pyfastaq/runners/to_random_subset.py
pyfastaq/runners/to_tiling_bam.py
pyfastaq/runners/to_unique_by_id.py
pyfastaq/runners/translate.py
pyfastaq/runners/trim_Ns_at_end.py
pyfastaq/runners/trim_contigs.py
pyfastaq/runners/trim_ends.py
pyfastaq/runners/version.py
pyfastaq-3.18.0.dist-info/METADATA
pyfastaq-3.18.0.dist-info/WHEEL
pyfastaq-3.18.0.dist-info/entry_points.txt
pyfastaq-3.18.0.dist-info/licenses/AUTHORS
pyfastaq-3.18.0.dist-info/licenses/LICENSE
pyfastaq-3.18.0.dist-info/RECORD
