Metadata-Version: 2.3
Name: pyfastaq
Version: 3.18.0
Summary: Script to manipulate FASTA and FASTQ files, plus API for developers.
Project-URL: homepage, https://github.com/sanger-pathogens/Fastaq
Project-URL: documentation, https://github.com/sanger-pathogens/Fastaq
Project-URL: repository, https://github.com/sanger-pathogens/Fastaq
Author-email: Martin Hunt <path-help@sanger.ac.uk>
License: GPLv3
Classifier: Development Status :: 4 - Beta
Classifier: License :: OSI Approved :: GNU General Public License v3 (GPLv3)
Classifier: Programming Language :: Python :: 3 :: Only
Classifier: Topic :: Scientific/Engineering :: Bio-Informatics
Requires-Python: >=3.8
Provides-Extra: tests
Requires-Dist: pytest; extra == 'tests'
